specialStr/__init__.py
specialStr/checker.py
specialStr/main.py
specialStr-0.1.1.dist-info/METADATA
specialStr-0.1.1.dist-info/WHEEL
specialStr-0.1.1.dist-info/top_level.txt
specialStr-0.1.1.dist-info/RECORD
